predict_collision/__init__.py
predict_collision/adaboost.py
predict_collision/grad_boost.py
predict_collision/knn.py
predict_collision/logistic.py
predict_collision/mlp.py
predict_collision/my_func.py
predict_collision/perceptron.py
predict_collision/random_forest.py
predict_collision/sgd.py
predict_collision/support_vector.py
predict_collision/visualize.py
predict_collision/xgboost.py
predict_the_object_collision-0.2.0.dist-info/LICENSE
predict_the_object_collision-0.2.0.dist-info/METADATA
predict_the_object_collision-0.2.0.dist-info/WHEEL
predict_the_object_collision-0.2.0.dist-info/top_level.txt
predict_the_object_collision-0.2.0.dist-info/RECORD
