Metadata-Version: 2.1
Name: predict-the-object-collision
Version: 0.2.0
Summary: The goal of this project is to predict the collision of nearest objects around the mighty EARTH.
Home-page: https://github.com/smn06/Predict-the-Collision-and-Save-the-Earth
Author: Sultan Mahmud Nahian
Author-email: sultanmahmud621@gmail.com
License: MIT
Platform: UNKNOWN
License-File: LICENSE
